mouseion/__init__.py
mouseion/train_and_build_index.py
mouseion-0.1.0.dist-info/METADATA
mouseion-0.1.0.dist-info/WHEEL
mouseion-0.1.0.dist-info/entry_points.txt
mouseion-0.1.0.dist-info/RECORD
